goldborn/__init__.py
goldborn/core.py
goldborn-0.1.0.dist-info/METADATA
goldborn-0.1.0.dist-info/WHEEL
goldborn-0.1.0.dist-info/top_level.txt
goldborn-0.1.0.dist-info/RECORD
