Metadata-Version: 2.4
Name: goldborn
Version: 0.1.0
Summary: A plotting library with golden ratio aesthetics, inspired by seaborn
Author-email: tolkeinenjoyer <tolkeinenjoyer@gmail.com>
Requires-Python: >=3.8
Requires-Dist: numpy
Requires-Dist: pandas
Requires-Dist: seaborn
Requires-Dist: matplotlib
